phoenixcat/__init__.py
phoenixcat/_init.py
phoenixcat/cli.py
phoenixcat/constant.py
phoenixcat/cuda.py
phoenixcat/environ.py
phoenixcat/parser.py
phoenixcat/welcome.py
phoenixcat/auto/__init__.py
phoenixcat/auto/accelerater_utils.py
phoenixcat/auto/autosave_utils.py
phoenixcat/auto/config_utils.py
phoenixcat/auto/dataclass_utils.py
phoenixcat/auto/dumper.py
phoenixcat/auto/pipeline_utils.py
phoenixcat/auto/version.py
phoenixcat/check/__init__.py
phoenixcat/check/check_args.py
phoenixcat/check/check_shape.py
phoenixcat/conversion/__init__.py
phoenixcat/conversion/get_object.py
phoenixcat/data/__init__.py
phoenixcat/data/accumulator.py
phoenixcat/data/counter.py
phoenixcat/decorators/__init__.py
phoenixcat/decorators/convert.py
phoenixcat/decorators/register.py
phoenixcat/download/__init__.py
phoenixcat/download/hugging_face/__init__.py
phoenixcat/download/hugging_face/api_download.py
phoenixcat/download/hugging_face/download.py
phoenixcat/download/hugging_face/mirror.py
phoenixcat/download/web/__init__.py
phoenixcat/download/web/get_file.py
phoenixcat/download/web/get_json.py
phoenixcat/download/web/url_split.py
phoenixcat/draw/__init__.py
phoenixcat/draw/linechart.py
phoenixcat/draw/utils.py
phoenixcat/files/__init__.py
phoenixcat/files/load.py
phoenixcat/files/manager.py
phoenixcat/files/path.py
phoenixcat/files/save.py
phoenixcat/files/walk.py
phoenixcat/format/__init__.py
phoenixcat/format/font_color.py
phoenixcat/format/format.py
phoenixcat/format/re_utils.py
phoenixcat/format/latex/__init__.py
phoenixcat/format/latex/table.py
phoenixcat/logger/__init__.py
phoenixcat/logger/logging.py
phoenixcat/models/__init__.py
phoenixcat/models/modeling_utils.py
phoenixcat/models/output.py
phoenixcat/models/classifiers/__init__.py
phoenixcat/models/classifiers/classifier_utils.py
phoenixcat/models/classifiers/external.py
phoenixcat/random/__init__.py
phoenixcat/random/_seeds.py
phoenixcat/random/string.py
phoenixcat/torchutils/__init__.py
phoenixcat/torchutils/batch.py
phoenixcat-0.6.0.dist-info/LICENSE
phoenixcat-0.6.0.dist-info/METADATA
phoenixcat-0.6.0.dist-info/WHEEL
phoenixcat-0.6.0.dist-info/entry_points.txt
phoenixcat-0.6.0.dist-info/top_level.txt
phoenixcat-0.6.0.dist-info/RECORD
