Metadata-Version: 2.1
Name: phoenixcat
Version: 0.6.0
Summary: An enhanced infrastructure library for PyTorch.
Home-page: https://github.com/Chrisqcwx/phoenixcat
Author: Hongyao Yu, Sijin Yu
Author-email: chrisqcwx@gmail.com, eeyusijin@mail.scut.edu.cn
License: Apache 2.0 License
Classifier: Development Status :: 2 - Pre-Alpha
Classifier: Intended Audience :: Developers
Classifier: Intended Audience :: Science/Research
Classifier: License :: OSI Approved :: Apache Software License
Classifier: Operating System :: OS Independent
Classifier: Programming Language :: Python :: 3
Classifier: Topic :: Scientific/Engineering :: Artificial Intelligence
Classifier: Topic :: Utilities
Requires-Python: >=3.8
License-File: LICENSE
Requires-Dist: torch
Requires-Dist: torchvision
Requires-Dist: diffusers
